goodness_of_fit/__init__.py
tests/__init__.py
tests/conftest.py
tests/test_goodness_of_fit.py
goodness_of_fit-1.0.1.dist-info/LICENSE.txt
goodness_of_fit-1.0.1.dist-info/METADATA
goodness_of_fit-1.0.1.dist-info/WHEEL
goodness_of_fit-1.0.1.dist-info/top_level.txt
goodness_of_fit-1.0.1.dist-info/RECORD
