Metadata-Version: 2.1
Name: goodness-of-fit
Version: 1.0.1
Summary: Function set for goodness of fit measure between two signals
Home-page: https://github.com/SimonDelmas/goodness_of_fit
Author: Simon Delmas
Author-email: delmas.simon@gmail.com
License: GLP-2.0
Platform: UNKNOWN
Classifier: Environment :: Console
Classifier: License :: OSI Approved :: GNU General Public License v2 (GPLv2)
Classifier: Programming Language :: Python :: 3
Classifier: Framework :: Pytest
Classifier: Intended Audience :: Science/Research
Requires-Dist: numpy
